remote_functions/__init__.py
remote_functions/interact.py
remote_functions/tools.py
remote_functions-1.0.1.dist-info/LICENSE
remote_functions-1.0.1.dist-info/METADATA
remote_functions-1.0.1.dist-info/WHEEL
remote_functions-1.0.1.dist-info/top_level.txt
remote_functions-1.0.1.dist-info/RECORD
