Metadata-Version: 2.1
Name: remote-functions
Version: 1.0.1
Summary: remote-functions provides type enforced remotely run Python functions
Home-page: https://github.com/jakestrouse00/remote-functions
Author: Jake Strouse
Author-email: jstrouse@meh.llc
License: UNKNOWN
Platform: UNKNOWN
Classifier: Programming Language :: Python :: 3
Classifier: License :: OSI Approved :: MIT License
Classifier: Operating System :: OS Independent
Requires-Python: >=3.7
License-File: LICENSE
Requires-Dist: fastapi[all]
Requires-Dist: uvicorn[standard]
Requires-Dist: requests (==2.27.1)
